modu.py
modu-0.1.1.dist-info/licenses/LICENSE
modu-0.1.1.dist-info/METADATA
modu-0.1.1.dist-info/WHEEL
modu-0.1.1.dist-info/top_level.txt
modu-0.1.1.dist-info/RECORD
