Metadata-Version: 2.4
Name: modu
Version: 0.1.1
Summary: Modular arithmetic in Python
Author-email: Pierre Denis <pie.denis@skynet.be>
Project-URL: Homepage, https://github.com/piedenis/Modu
Project-URL: Bug Tracker, https://github.com/piedenis/Modu/issues
Classifier: Development Status :: 4 - Beta
Classifier: Programming Language :: Python :: 3
Classifier: License :: OSI Approved :: MIT License
Classifier: Operating System :: OS Independent
Classifier: Topic :: Scientific/Engineering :: Mathematics
Requires-Python: >=3.9
License-File: LICENSE
Dynamic: license-file
